lunarcrushed/__init__.py
lunarcrushed/__main__.py
lunarcrushed-0.1.2.dist-info/LICENSE
lunarcrushed-0.1.2.dist-info/METADATA
lunarcrushed-0.1.2.dist-info/WHEEL
lunarcrushed-0.1.2.dist-info/top_level.txt
lunarcrushed-0.1.2.dist-info/RECORD
